nome_do_projeto/__init__.py
nome_do_projeto-0.1.0.dist-info/METADATA
nome_do_projeto-0.1.0.dist-info/WHEEL
nome_do_projeto-0.1.0.dist-info/RECORD
