Metadata-Version: 2.1
Name: nome-do-projeto
Version: 0.1.0
Summary: Projeto de exemplo
Author: Daniele Santiago
Author-email: daniellestg6@gmail.com
Requires-Python: >=3.12,<4.0
Classifier: Programming Language :: Python :: 3
Classifier: Programming Language :: Python :: 3.12
Classifier: Programming Language :: Python :: 3.13
Requires-Dist: numpy (>=2.2.1,<3.0.0)
